wbclione/__init__.py
wbclione/api.py
wbclione/cli.py
wbclione/run_manager.py
wbclione/util.py
wbclione-0.1.1.1.dist-info/METADATA
wbclione-0.1.1.1.dist-info/WHEEL
wbclione-0.1.1.1.dist-info/entry_points.txt
wbclione-0.1.1.1.dist-info/top_level.txt
wbclione-0.1.1.1.dist-info/RECORD
